mcp_web_extractor-0.1.1.dist-info/licenses/LICENSE
web_extractor/__init__.py
web_extractor/server.py
mcp_web_extractor-0.1.1.dist-info/METADATA
mcp_web_extractor-0.1.1.dist-info/WHEEL
mcp_web_extractor-0.1.1.dist-info/entry_points.txt
mcp_web_extractor-0.1.1.dist-info/top_level.txt
mcp_web_extractor-0.1.1.dist-info/RECORD
